videoall/__init__.py
videoall/video.py
videoall/sources/__init__.py
videoall/sources/acfun.py
videoall/sources/baidutieba.py
videoall/sources/base.py
videoall/sources/bilibili.py
videoall/sources/cntv.py
videoall/sources/douyin.py
videoall/sources/haokan.py
videoall/sources/iqiyi.py
videoall/sources/ku6.py
videoall/sources/kuaishou.py
videoall/sources/mgtv.py
videoall/sources/migu.py
videoall/sources/pipigaoxiao.py
videoall/sources/pipix.py
videoall/sources/sohu.py
videoall/sources/ted.py
videoall/sources/weibo.py
videoall/sources/xigua.py
videoall/sources/yinyuetai.py
videoall/sources/zhihu.py
videoall/utils/__init__.py
videoall/utils/downloader.py
videoall/utils/logger.py
videoall/utils/misc.py
videoall-0.0.6.dist-info/LICENSE
videoall-0.0.6.dist-info/METADATA
videoall-0.0.6.dist-info/WHEEL
videoall-0.0.6.dist-info/top_level.txt
videoall-0.0.6.dist-info/RECORD
