Metadata-Version: 2.1
Name: videoall
Version: 0.0.6
Summary: All video download
Home-page: https://github.com/cocpy/VideoAll
Author: C灵C
Author-email: c0c@cocpy.com
License: UNKNOWN
Platform: UNKNOWN
Classifier: Programming Language :: Python :: 3
Classifier: License :: OSI Approved :: MIT License
Classifier: Operating System :: OS Independent
